pybrafile/__init__.py
pybrafile/file.py
pybrafile-0.1.3.dist-info/LICENSE
pybrafile-0.1.3.dist-info/METADATA
pybrafile-0.1.3.dist-info/WHEEL
pybrafile-0.1.3.dist-info/RECORD
