Metadata-Version: 2.1
Name: pybrafile
Version: 0.1.3
Summary: Brainstorming package to manage texte files
License: MIT
Author: Brainstorming
Author-email: Support.erp@brainstorming.eu
Requires-Python: >=3.10,<4.0
Classifier: License :: OSI Approved :: MIT License
Classifier: Programming Language :: Python :: 3
Classifier: Programming Language :: Python :: 3.10
Classifier: Programming Language :: Python :: 3.11
Classifier: Programming Language :: Python :: 3.12
